nmrml2isa/__init__.py
nmrml2isa/__main__.py
nmrml2isa/isa.py
nmrml2isa/nmrCV.owl
nmrml2isa/nmrml.py
nmrml2isa/parsing.py
nmrml2isa/usermeta.py
nmrml2isa/utils.py
nmrml2isa/default/a_nmrML.txt
nmrml2isa/default/i_nmrML.txt
nmrml2isa/default/s_nmrML.txt
tests/__init__.py
tests/abstract_test_isa.py
tests/test_mtbls.py
tests/test_nmrml_examples.py
tests/utils.py
nmrml2isa-0.3.3.dist-info/COPYING
nmrml2isa-0.3.3.dist-info/METADATA
nmrml2isa-0.3.3.dist-info/WHEEL
nmrml2isa-0.3.3.dist-info/entry_points.txt
nmrml2isa-0.3.3.dist-info/top_level.txt
nmrml2isa-0.3.3.dist-info/RECORD
