Metadata-Version: 2.1
Name: nmrml2isa
Version: 0.3.3
Summary: nmrml2isa - nmrML to ISA-Tab parsing tool
Home-page: http://github.com/althonos/nmrml2isa
Author: Martin Larralde
Author-email: martin.larralde@ens-cachan.fr
License: GPLv3
Keywords: Metabolomics,NMR,Nuclear Magnetic Resonance,ISA Tab,nmrML,metabolites,parsing
Classifier: Programming Language :: Python :: 2
Classifier: Programming Language :: Python :: 2.7
Classifier: Programming Language :: Python :: 3
Classifier: Programming Language :: Python :: 3.5
Classifier: Programming Language :: Python :: 3.6
Classifier: Programming Language :: Python :: 3.7
Classifier: Programming Language :: Python :: 3.8
Classifier: Programming Language :: Python :: 3.9
Classifier: Topic :: Text Processing :: Markup :: XML
Classifier: Topic :: Scientific/Engineering :: Bio-Informatics
Classifier: Topic :: Scientific/Engineering :: Chemistry
Classifier: Topic :: Utilities
Classifier: License :: OSI Approved :: GNU General Public License v3 (GPLv3)
Classifier: Operating System :: OS Independent
License-File: COPYING
Requires-Dist: six
Requires-Dist: pronto ~=0.6
Requires-Dist: openpyxl
